{
  "gitSyncId": "69e5ff1222f495834779eb8e_e01e31c5-ccea-47db-89d6-8a2c32a4e8d9",
  "id": "TestResultEntry_Api_ReadMastersRecommendations",
  "pluginId": "restapi-plugin",
  "pluginType": "API",
  "unpublishedAction": {
    "actionConfiguration": {
      "autoGeneratedHeaders": [],
      "body": "",
      "bodyFormData": [],
      "encodeParamsToggle": true,
      "formData": {
        "apiContentType": "none"
      },
      "headers": [],
      "httpMethod": "GET",
      "httpVersion": "HTTP11",
      "paginationType": "NONE",
      "path": "/masters/recommendations",
      "pluginSpecifiedTemplates": [
        {
          "value": true
        }
      ],
      "queryParameters": [],
      "timeoutInMillisecond": 10000
    },
    "confirmBeforeExecute": false,
    "datasource": {
      "id": "oralytics_sqlite",
      "isAutoGenerated": false,
      "name": "oralytics_sqlite",
      "pluginId": "restapi-plugin"
    },
    "dynamicBindingPathList": [],
    "name": "Api_ReadMastersRecommendations",
    "pageId": "TestResultEntry",
    "runBehaviour": "MANUAL",
    "userSetOnLoad": false
  }
}